scopper/__init__.py
scopper-0.1.dist-info/METADATA
scopper-0.1.dist-info/WHEEL
scopper-0.1.dist-info/top_level.txt
scopper-0.1.dist-info/RECORD
