Metadata-Version: 2.4
Name: scopper
Version: 0.1
Summary: Simple Scopper Library
Author: Elijah Joseph
Classifier: Programming Language :: Python :: 3
Requires-Python: >=3.6
Dynamic: author
Dynamic: classifier
Dynamic: requires-python
Dynamic: summary
